physionet_mcp/__init__.py
physionet_mcp/mcp_server.py
physionet_mcp-0.0.2.dist-info/METADATA
physionet_mcp-0.0.2.dist-info/WHEEL
physionet_mcp-0.0.2.dist-info/entry_points.txt
physionet_mcp-0.0.2.dist-info/licenses/LICENSE
physionet_mcp-0.0.2.dist-info/RECORD
