Metadata-Version: 2.4
Name: physionet-mcp
Version: 0.0.2
Summary: Lean BigQuery-only MCP server for PhysioNet datasets
Project-URL: Homepage, https://github.com/rafiattrach/physionet-mcp
Project-URL: Repository, https://github.com/rafiattrach/physionet-mcp
Project-URL: Issues, https://github.com/rafiattrach/physionet-mcp/issues
Author-email: Rafi Al Attrach <rafiaa@mit.edu>, Pedro Moreira <pedrojfm@mit.edu>, Rajna Fani <rajnaf@mit.edu>
License-Expression: MIT
License-File: LICENSE
Classifier: Development Status :: 3 - Alpha
Classifier: Intended Audience :: Healthcare Industry
Classifier: Intended Audience :: Science/Research
Classifier: Operating System :: OS Independent
Classifier: Programming Language :: Python :: 3
Classifier: Programming Language :: Python :: 3.10
Classifier: Programming Language :: Python :: 3.11
Classifier: Programming Language :: Python :: 3.12
Classifier: Topic :: Scientific/Engineering :: Medical Science Apps.
Requires-Python: >=3.10
Requires-Dist: db-dtypes>=1.0.0
Requires-Dist: fastmcp>=0.1.0
Requires-Dist: google-cloud-bigquery>=3.0.0
Requires-Dist: pandas>=2.0.0
Requires-Dist: sqlparse>=0.4.0
